helloworld/__init__.py
helloworld_codemicro-1.0.0.dist-info/LICENCE
helloworld_codemicro-1.0.0.dist-info/METADATA
helloworld_codemicro-1.0.0.dist-info/WHEEL
helloworld_codemicro-1.0.0.dist-info/top_level.txt
helloworld_codemicro-1.0.0.dist-info/RECORD
