Metadata-Version: 2.1
Name: helloworld-codemicro
Version: 1.0.0
Summary: A testing package to be uploaded to PyPI
Home-page: https://www.github.com/codemicro/helloworld-python
Author: Thomas Pain
Author-email: tom@tdpain.net
License: UNKNOWN
Platform: UNKNOWN
Requires-Python: >=3.5
